{
  "lastUpdated": "2026-04-26T09:47:52.417241",
  "categories": {
    "auto": [
      {
        "category": "auto",
        "emoji": "\ud83d\ude97",
        "applicant": "Jinhua Mingwan Auto Parts Co., Ltd.",
        "mark": "SELROEY",
        "serial": "99784109",
        "date": "2026-04-24",
        "url": "https://tsdr.uspto.gov/#caseNumber=99784109&caseSearchType=US_APPLICATION&caseType=DEFAULT&searchType=statusSearch"
      }
    ],
    "gaming": [
      {
        "category": "gaming",
        "emoji": "\ud83c\udfae",
        "applicant": "Eldridge V Felder",
        "mark": "ABRAMS: STEEL RESOLVE",
        "serial": "99786410",
        "date": "2026-04-24",
        "url": "https://tsdr.uspto.gov/#caseNumber=99786410&caseSearchType=US_APPLICATION&caseType=DEFAULT&searchType=statusSearch"
      },
      {
        "category": "gaming",
        "emoji": "\ud83c\udfae",
        "applicant": "LIGHT & WONDER, INC.",
        "mark": "FAT N' HAPPY",
        "serial": "99178874",
        "date": "2025-05-10",
        "url": "https://tsdr.uspto.gov/#caseNumber=99178874&caseSearchType=US_APPLICATION&caseType=DEFAULT&searchType=statusSearch"
      }
    ],
    "crypto": [
      {
        "category": "crypto",
        "emoji": "\ud83e\ude99",
        "applicant": "Quickswap Corp.",
        "mark": "QUICKSWAP",
        "serial": "99784143",
        "date": "2026-04-24",
        "url": "https://tsdr.uspto.gov/#caseNumber=99784143&caseSearchType=US_APPLICATION&caseType=DEFAULT&searchType=statusSearch"
      }
    ],
    "celebrities": [],
    "tech": [
      {
        "category": "tech",
        "emoji": "\ud83d\udcbb",
        "applicant": "AURELIUS CANON LLC",
        "mark": "AURELIUS CANON",
        "serial": "99786289",
        "date": "2026-04-24",
        "url": "https://tsdr.uspto.gov/#caseNumber=99786289&caseSearchType=US_APPLICATION&caseType=DEFAULT&searchType=statusSearch"
      },
      {
        "category": "tech",
        "emoji": "\ud83d\udcbb",
        "applicant": "Aerobotics7, Inc.",
        "mark": "UNDEREARTH INTELLIGENCE",
        "serial": "99786323",
        "date": "2026-04-24",
        "url": "https://tsdr.uspto.gov/#caseNumber=99786323&caseSearchType=US_APPLICATION&caseType=DEFAULT&searchType=statusSearch"
      },
      {
        "category": "tech",
        "emoji": "\ud83d\udcbb",
        "applicant": "Acutus Partners, LLC",
        "mark": "THE UNSEEN MOVE",
        "serial": "99786394",
        "date": "2026-04-24",
        "url": "https://tsdr.uspto.gov/#caseNumber=99786394&caseSearchType=US_APPLICATION&caseType=DEFAULT&searchType=statusSearch"
      },
      {
        "category": "tech",
        "emoji": "\ud83d\udcbb",
        "applicant": "Nieto Engineering, Inc.",
        "mark": "NEI SERVICES",
        "serial": "99786432",
        "date": "2026-04-24",
        "url": "https://tsdr.uspto.gov/#caseNumber=99786432&caseSearchType=US_APPLICATION&caseType=DEFAULT&searchType=statusSearch"
      },
      {
        "category": "tech",
        "emoji": "\ud83d\udcbb",
        "applicant": "Safety Logic LLC",
        "mark": "WIND LANE",
        "serial": "99786448",
        "date": "2026-04-24",
        "url": "https://tsdr.uspto.gov/#caseNumber=99786448&caseSearchType=US_APPLICATION&caseType=DEFAULT&searchType=statusSearch"
      },
      {
        "category": "tech",
        "emoji": "\ud83d\udcbb",
        "applicant": "LINGEQ TECHNOLOGIES LIMITED",
        "mark": "LEQ LINGEQ INSIDE LINGEQ INSIDE",
        "serial": "99786449",
        "date": "2026-04-24",
        "url": "https://tsdr.uspto.gov/#caseNumber=99786449&caseSearchType=US_APPLICATION&caseType=DEFAULT&searchType=statusSearch"
      },
      {
        "category": "tech",
        "emoji": "\ud83d\udcbb",
        "applicant": "LINGEQ TECHNOLOGIES LIMITED",
        "mark": "LEQ LINGEQ INSIDE",
        "serial": "99786453",
        "date": "2026-04-24",
        "url": "https://tsdr.uspto.gov/#caseNumber=99786453&caseSearchType=US_APPLICATION&caseType=DEFAULT&searchType=statusSearch"
      },
      {
        "category": "tech",
        "emoji": "\ud83d\udcbb",
        "applicant": "Beijing Shengshu Technology Co., Ltd.",
        "mark": "(Logo Only)",
        "serial": "99786455",
        "date": "2026-04-24",
        "url": "https://tsdr.uspto.gov/#caseNumber=99786455&caseSearchType=US_APPLICATION&caseType=DEFAULT&searchType=statusSearch"
      },
      {
        "category": "tech",
        "emoji": "\ud83d\udcbb",
        "applicant": "Beijing Shengshu Technology Co., Ltd.",
        "mark": "(Logo Only)",
        "serial": "99786467",
        "date": "2026-04-24",
        "url": "https://tsdr.uspto.gov/#caseNumber=99786467&caseSearchType=US_APPLICATION&caseType=DEFAULT&searchType=statusSearch"
      },
      {
        "category": "tech",
        "emoji": "\ud83d\udcbb",
        "applicant": "Beijing Shengshu Technology Co., Ltd.",
        "mark": "(Logo Only)",
        "serial": "99786477",
        "date": "2026-04-24",
        "url": "https://tsdr.uspto.gov/#caseNumber=99786477&caseSearchType=US_APPLICATION&caseType=DEFAULT&searchType=statusSearch"
      },
      {
        "category": "tech",
        "emoji": "\ud83d\udcbb",
        "applicant": "Badge Six, LLC",
        "mark": "THIS IS ACCREDITATION: SIMPLIFIED - THIS IS BADGE 6",
        "serial": "99784101",
        "date": "2026-04-24",
        "url": "https://tsdr.uspto.gov/#caseNumber=99784101&caseSearchType=US_APPLICATION&caseType=DEFAULT&searchType=statusSearch"
      },
      {
        "category": "tech",
        "emoji": "\ud83d\udcbb",
        "applicant": "Kyle Fecik",
        "mark": "POSEUR",
        "serial": "99784107",
        "date": "2026-04-24",
        "url": "https://tsdr.uspto.gov/#caseNumber=99784107&caseSearchType=US_APPLICATION&caseType=DEFAULT&searchType=statusSearch"
      },
      {
        "category": "tech",
        "emoji": "\ud83d\udcbb",
        "applicant": "Gold Inc.",
        "mark": "GOLD AI",
        "serial": "99784111",
        "date": "2026-04-24",
        "url": "https://tsdr.uspto.gov/#caseNumber=99784111&caseSearchType=US_APPLICATION&caseType=DEFAULT&searchType=statusSearch"
      },
      {
        "category": "tech",
        "emoji": "\ud83d\udcbb",
        "applicant": "Real Estate Systems Architect LLC",
        "mark": "GET RENT VERIFIED",
        "serial": "99784137",
        "date": "2026-04-24",
        "url": "https://tsdr.uspto.gov/#caseNumber=99784137&caseSearchType=US_APPLICATION&caseType=DEFAULT&searchType=statusSearch"
      },
      {
        "category": "tech",
        "emoji": "\ud83d\udcbb",
        "applicant": "FEASTER FOOD LLC",
        "mark": "FEASTER",
        "serial": "99784149",
        "date": "2026-04-24",
        "url": "https://tsdr.uspto.gov/#caseNumber=99784149&caseSearchType=US_APPLICATION&caseType=DEFAULT&searchType=statusSearch"
      },
      {
        "category": "tech",
        "emoji": "\ud83d\udcbb",
        "applicant": "iPolish, Inc.",
        "mark": "I (& Logo)",
        "serial": "99179072",
        "date": "2025-05-10",
        "url": "https://tsdr.uspto.gov/#caseNumber=99179072&caseSearchType=US_APPLICATION&caseType=DEFAULT&searchType=statusSearch"
      },
      {
        "category": "tech",
        "emoji": "\ud83d\udcbb",
        "applicant": "Jenny Patrizia Lee",
        "mark": "EMOTIONAL SUPPORT AI",
        "serial": "99178810",
        "date": "2025-05-10",
        "url": "https://tsdr.uspto.gov/#caseNumber=99178810&caseSearchType=US_APPLICATION&caseType=DEFAULT&searchType=statusSearch"
      },
      {
        "category": "tech",
        "emoji": "\ud83d\udcbb",
        "applicant": "Aifection LLC",
        "mark": "HEARTCHIP",
        "serial": "99178827",
        "date": "2025-05-10",
        "url": "https://tsdr.uspto.gov/#caseNumber=99178827&caseSearchType=US_APPLICATION&caseType=DEFAULT&searchType=statusSearch"
      },
      {
        "category": "tech",
        "emoji": "\ud83d\udcbb",
        "applicant": "DiscoverFire.ai LLC",
        "mark": "DISCOVERFIRE AI (& Logo)",
        "serial": "99178834",
        "date": "2025-05-10",
        "url": "https://tsdr.uspto.gov/#caseNumber=99178834&caseSearchType=US_APPLICATION&caseType=DEFAULT&searchType=statusSearch"
      },
      {
        "category": "tech",
        "emoji": "\ud83d\udcbb",
        "applicant": "Reclusive Inc.",
        "mark": "CLOSED-CIRCUIT AI",
        "serial": "99179115",
        "date": "2025-05-10",
        "url": "https://tsdr.uspto.gov/#caseNumber=99179115&caseSearchType=US_APPLICATION&caseType=DEFAULT&searchType=statusSearch"
      }
    ],
    "sports": [],
    "music": [
      {
        "category": "music",
        "emoji": "\ud83c\udfb5",
        "applicant": "Silicronica Music, LLC",
        "mark": "SILICRONICA MUSIC",
        "serial": "99784119",
        "date": "2026-04-24",
        "url": "https://tsdr.uspto.gov/#caseNumber=99784119&caseSearchType=US_APPLICATION&caseType=DEFAULT&searchType=statusSearch"
      }
    ],
    "entertainment": [
      {
        "category": "entertainment",
        "emoji": "\ud83c\udfac",
        "applicant": "Nicholas Gladieux",
        "mark": "NYXON",
        "serial": "99786211",
        "date": "2026-04-24",
        "url": "https://tsdr.uspto.gov/#caseNumber=99786211&caseSearchType=US_APPLICATION&caseType=DEFAULT&searchType=statusSearch"
      },
      {
        "category": "entertainment",
        "emoji": "\ud83c\udfac",
        "applicant": "Sea Soil Sky LLC",
        "mark": "SEA.SOIL.SKY",
        "serial": "99778733",
        "date": "2026-04-24",
        "url": "https://tsdr.uspto.gov/#caseNumber=99778733&caseSearchType=US_APPLICATION&caseType=DEFAULT&searchType=statusSearch"
      },
      {
        "category": "entertainment",
        "emoji": "\ud83c\udfac",
        "applicant": "Daniel Robert TARR-PINTER",
        "mark": "42NET (& Logo)",
        "serial": "99179012",
        "date": "2025-05-10",
        "url": "https://tsdr.uspto.gov/#caseNumber=99179012&caseSearchType=US_APPLICATION&caseType=DEFAULT&searchType=statusSearch"
      },
      {
        "category": "entertainment",
        "emoji": "\ud83c\udfac",
        "applicant": "cloaq media",
        "mark": "THE DARK ROOM",
        "serial": "99178852",
        "date": "2025-05-10",
        "url": "https://tsdr.uspto.gov/#caseNumber=99178852&caseSearchType=US_APPLICATION&caseType=DEFAULT&searchType=statusSearch"
      },
      {
        "category": "entertainment",
        "emoji": "\ud83c\udfac",
        "applicant": "Wendy Jimenez",
        "mark": "ANGEL ARTISTS",
        "serial": "99178898",
        "date": "2025-05-10",
        "url": "https://tsdr.uspto.gov/#caseNumber=99178898&caseSearchType=US_APPLICATION&caseType=DEFAULT&searchType=statusSearch"
      }
    ],
    "food": [
      {
        "category": "food",
        "emoji": "\ud83c\udf54",
        "applicant": "Cassandra Bruny",
        "mark": "BROWNED & BUTTER",
        "serial": "99786325",
        "date": "2026-04-24",
        "url": "https://tsdr.uspto.gov/#caseNumber=99786325&caseSearchType=US_APPLICATION&caseType=DEFAULT&searchType=statusSearch"
      },
      {
        "category": "food",
        "emoji": "\ud83c\udf54",
        "applicant": "Tsion Trading LLC",
        "mark": "MARAKI INJERA",
        "serial": "99786347",
        "date": "2026-04-24",
        "url": "https://tsdr.uspto.gov/#caseNumber=99786347&caseSearchType=US_APPLICATION&caseType=DEFAULT&searchType=statusSearch"
      },
      {
        "category": "food",
        "emoji": "\ud83c\udf54",
        "applicant": "Haixing XUE",
        "mark": "POIMHEW",
        "serial": "99786380",
        "date": "2026-04-24",
        "url": "https://tsdr.uspto.gov/#caseNumber=99786380&caseSearchType=US_APPLICATION&caseType=DEFAULT&searchType=statusSearch"
      },
      {
        "category": "food",
        "emoji": "\ud83c\udf54",
        "applicant": "Taty's LLC",
        "mark": "TATY'S TACOS & MARGARITAS",
        "serial": "99784120",
        "date": "2026-04-24",
        "url": "https://tsdr.uspto.gov/#caseNumber=99784120&caseSearchType=US_APPLICATION&caseType=DEFAULT&searchType=statusSearch"
      },
      {
        "category": "food",
        "emoji": "\ud83c\udf54",
        "applicant": "jnarazurum llc",
        "mark": "JNARA",
        "serial": "99178217",
        "date": "2025-05-11",
        "url": "https://tsdr.uspto.gov/#caseNumber=99178217&caseSearchType=US_APPLICATION&caseType=DEFAULT&searchType=statusSearch"
      },
      {
        "category": "food",
        "emoji": "\ud83c\udf54",
        "applicant": "Mission 618 Inc.",
        "mark": "CHICK CHICK",
        "serial": "99178923",
        "date": "2025-05-10",
        "url": "https://tsdr.uspto.gov/#caseNumber=99178923&caseSearchType=US_APPLICATION&caseType=DEFAULT&searchType=statusSearch"
      }
    ],
    "beverage": [
      {
        "category": "beverage",
        "emoji": "\ud83e\udd64",
        "applicant": "Jennifer Rodriguez",
        "mark": "QU\u00c9",
        "serial": "99786368",
        "date": "2026-04-24",
        "url": "https://tsdr.uspto.gov/#caseNumber=99786368&caseSearchType=US_APPLICATION&caseType=DEFAULT&searchType=statusSearch"
      },
      {
        "category": "beverage",
        "emoji": "\ud83e\udd64",
        "applicant": "Jiajia CHAO",
        "mark": "KTYEOD",
        "serial": "99786408",
        "date": "2026-04-24",
        "url": "https://tsdr.uspto.gov/#caseNumber=99786408&caseSearchType=US_APPLICATION&caseType=DEFAULT&searchType=statusSearch"
      },
      {
        "category": "beverage",
        "emoji": "\ud83e\udd64",
        "applicant": "Andr\u00e9 Benjamin",
        "mark": "BENJI BIXBY",
        "serial": "99178824",
        "date": "2025-05-10",
        "url": "https://tsdr.uspto.gov/#caseNumber=99178824&caseSearchType=US_APPLICATION&caseType=DEFAULT&searchType=statusSearch"
      }
    ],
    "fashion": [
      {
        "category": "fashion",
        "emoji": "\ud83d\udc5f",
        "applicant": "Xiamen Yunhe Times Supply Chain Management Co., Ltd.",
        "mark": "COORA",
        "serial": "99786257",
        "date": "2026-04-24",
        "url": "https://tsdr.uspto.gov/#caseNumber=99786257&caseSearchType=US_APPLICATION&caseType=DEFAULT&searchType=statusSearch"
      },
      {
        "category": "fashion",
        "emoji": "\ud83d\udc5f",
        "applicant": "Lynette Alberta Long",
        "mark": "BORN PINK IN A BLUE WORLD (& Logo)",
        "serial": "99786284",
        "date": "2026-04-24",
        "url": "https://tsdr.uspto.gov/#caseNumber=99786284&caseSearchType=US_APPLICATION&caseType=DEFAULT&searchType=statusSearch"
      },
      {
        "category": "fashion",
        "emoji": "\ud83d\udc5f",
        "applicant": "MYNPYK LLC",
        "mark": "GODS FAVORED",
        "serial": "99786397",
        "date": "2026-04-24",
        "url": "https://tsdr.uspto.gov/#caseNumber=99786397&caseSearchType=US_APPLICATION&caseType=DEFAULT&searchType=statusSearch"
      },
      {
        "category": "fashion",
        "emoji": "\ud83d\udc5f",
        "applicant": "Etoni T Tonga",
        "mark": "SLON8VE",
        "serial": "99178906",
        "date": "2025-05-10",
        "url": "https://tsdr.uspto.gov/#caseNumber=99178906&caseSearchType=US_APPLICATION&caseType=DEFAULT&searchType=statusSearch"
      }
    ]
  }
}