{
  "lastUpdated": "2025-08-29T09:14:59.389597",
  "categories": {
    "auto": [
      {
        "category": "auto",
        "emoji": "\ud83d\ude97",
        "applicant": "Huantao Zhao",
        "mark": "LIKEVER",
        "serial": "99361882",
        "date": "2025-08-27",
        "url": "https://tsdr.uspto.gov/#caseNumber=99361882&caseSearchType=US_APPLICATION&caseType=DEFAULT&searchType=statusSearch"
      },
      {
        "category": "auto",
        "emoji": "\ud83d\ude97",
        "applicant": "WENZHOU XIANFENG AUTO PARTS TRADING CO., LTD.",
        "mark": "VASTAUTO",
        "serial": "99361942",
        "date": "2025-08-27",
        "url": "https://tsdr.uspto.gov/#caseNumber=99361942&caseSearchType=US_APPLICATION&caseType=DEFAULT&searchType=statusSearch"
      }
    ],
    "gaming": [
      {
        "category": "gaming",
        "emoji": "\ud83c\udfae",
        "applicant": "LIGHT & WONDER, INC.",
        "mark": "FAT N' HAPPY",
        "serial": "99178874",
        "date": "2025-05-10",
        "url": "https://tsdr.uspto.gov/#caseNumber=99178874&caseSearchType=US_APPLICATION&caseType=DEFAULT&searchType=statusSearch"
      }
    ],
    "crypto": [
      {
        "category": "crypto",
        "emoji": "\ud83e\ude99",
        "applicant": "Snek Foundation",
        "mark": "SNEK (& Logo)",
        "serial": "99359978",
        "date": "2025-08-27",
        "url": "https://tsdr.uspto.gov/#caseNumber=99359978&caseSearchType=US_APPLICATION&caseType=DEFAULT&searchType=statusSearch"
      }
    ],
    "celebrities": [],
    "tech": [
      {
        "category": "tech",
        "emoji": "\ud83d\udcbb",
        "applicant": "Brandon Okeith Smith",
        "mark": "VR ADVENTURES",
        "serial": "99361711",
        "date": "2025-08-27",
        "url": "https://tsdr.uspto.gov/#caseNumber=99361711&caseSearchType=US_APPLICATION&caseType=DEFAULT&searchType=statusSearch"
      },
      {
        "category": "tech",
        "emoji": "\ud83d\udcbb",
        "applicant": "PhysicalCash LLC",
        "mark": "ATMLESS",
        "serial": "99361716",
        "date": "2025-08-27",
        "url": "https://tsdr.uspto.gov/#caseNumber=99361716&caseSearchType=US_APPLICATION&caseType=DEFAULT&searchType=statusSearch"
      },
      {
        "category": "tech",
        "emoji": "\ud83d\udcbb",
        "applicant": "Mundial Media, Inc.",
        "mark": "CADMUS AI",
        "serial": "99361721",
        "date": "2025-08-27",
        "url": "https://tsdr.uspto.gov/#caseNumber=99361721&caseSearchType=US_APPLICATION&caseType=DEFAULT&searchType=statusSearch"
      },
      {
        "category": "tech",
        "emoji": "\ud83d\udcbb",
        "applicant": "Zhen Chen",
        "mark": "ZOETEC",
        "serial": "99359923",
        "date": "2025-08-27",
        "url": "https://tsdr.uspto.gov/#caseNumber=99359923&caseSearchType=US_APPLICATION&caseType=DEFAULT&searchType=statusSearch"
      },
      {
        "category": "tech",
        "emoji": "\ud83d\udcbb",
        "applicant": "SUBCRAFT.AI, INC.",
        "mark": "S SUBCRAFT.AI",
        "serial": "99359932",
        "date": "2025-08-27",
        "url": "https://tsdr.uspto.gov/#caseNumber=99359932&caseSearchType=US_APPLICATION&caseType=DEFAULT&searchType=statusSearch"
      },
      {
        "category": "tech",
        "emoji": "\ud83d\udcbb",
        "applicant": "SUBCRAFT.AI, INC.",
        "mark": "S",
        "serial": "99359936",
        "date": "2025-08-27",
        "url": "https://tsdr.uspto.gov/#caseNumber=99359936&caseSearchType=US_APPLICATION&caseType=DEFAULT&searchType=statusSearch"
      },
      {
        "category": "tech",
        "emoji": "\ud83d\udcbb",
        "applicant": "SUBCRAFT.AI, INC.",
        "mark": "RECOVER REVENUE. REDUCE CHURN. RETAIN CUSTOMERS.",
        "serial": "99359943",
        "date": "2025-08-27",
        "url": "https://tsdr.uspto.gov/#caseNumber=99359943&caseSearchType=US_APPLICATION&caseType=DEFAULT&searchType=statusSearch"
      },
      {
        "category": "tech",
        "emoji": "\ud83d\udcbb",
        "applicant": "SUBCRAFT.AI, INC.",
        "mark": "SUBCRAFT.AI",
        "serial": "99359950",
        "date": "2025-08-27",
        "url": "https://tsdr.uspto.gov/#caseNumber=99359950&caseSearchType=US_APPLICATION&caseType=DEFAULT&searchType=statusSearch"
      },
      {
        "category": "tech",
        "emoji": "\ud83d\udcbb",
        "applicant": "Brandon Dune",
        "mark": "EZVNTS",
        "serial": "99359961",
        "date": "2025-08-27",
        "url": "https://tsdr.uspto.gov/#caseNumber=99359961&caseSearchType=US_APPLICATION&caseType=DEFAULT&searchType=statusSearch"
      },
      {
        "category": "tech",
        "emoji": "\ud83d\udcbb",
        "applicant": "Aperio Global, LLC",
        "mark": "EXCELLENCE WITHOUT EXCUSES",
        "serial": "99359972",
        "date": "2025-08-27",
        "url": "https://tsdr.uspto.gov/#caseNumber=99359972&caseSearchType=US_APPLICATION&caseType=DEFAULT&searchType=statusSearch"
      },
      {
        "category": "tech",
        "emoji": "\ud83d\udcbb",
        "applicant": "Aperio Global, LLC",
        "mark": "TRUTH, TRUST AND TRANSPARENCY",
        "serial": "99359973",
        "date": "2025-08-27",
        "url": "https://tsdr.uspto.gov/#caseNumber=99359973&caseSearchType=US_APPLICATION&caseType=DEFAULT&searchType=statusSearch"
      },
      {
        "category": "tech",
        "emoji": "\ud83d\udcbb",
        "applicant": "Board AI, Inc.",
        "mark": "VALLOR",
        "serial": "99359993",
        "date": "2025-08-27",
        "url": "https://tsdr.uspto.gov/#caseNumber=99359993&caseSearchType=US_APPLICATION&caseType=DEFAULT&searchType=statusSearch"
      },
      {
        "category": "tech",
        "emoji": "\ud83d\udcbb",
        "applicant": "LEOTEK CORPORATION",
        "mark": "LEOTEK RENAI",
        "serial": "99360036",
        "date": "2025-08-27",
        "url": "https://tsdr.uspto.gov/#caseNumber=99360036&caseSearchType=US_APPLICATION&caseType=DEFAULT&searchType=statusSearch"
      },
      {
        "category": "tech",
        "emoji": "\ud83d\udcbb",
        "applicant": "iPolish, Inc.",
        "mark": "I (& Logo)",
        "serial": "99179072",
        "date": "2025-05-10",
        "url": "https://tsdr.uspto.gov/#caseNumber=99179072&caseSearchType=US_APPLICATION&caseType=DEFAULT&searchType=statusSearch"
      },
      {
        "category": "tech",
        "emoji": "\ud83d\udcbb",
        "applicant": "Jenny Patrizia Lee",
        "mark": "EMOTIONAL SUPPORT AI",
        "serial": "99178810",
        "date": "2025-05-10",
        "url": "https://tsdr.uspto.gov/#caseNumber=99178810&caseSearchType=US_APPLICATION&caseType=DEFAULT&searchType=statusSearch"
      },
      {
        "category": "tech",
        "emoji": "\ud83d\udcbb",
        "applicant": "Aifection LLC",
        "mark": "HEARTCHIP",
        "serial": "99178827",
        "date": "2025-05-10",
        "url": "https://tsdr.uspto.gov/#caseNumber=99178827&caseSearchType=US_APPLICATION&caseType=DEFAULT&searchType=statusSearch"
      },
      {
        "category": "tech",
        "emoji": "\ud83d\udcbb",
        "applicant": "DiscoverFire.ai LLC",
        "mark": "DISCOVERFIRE AI (& Logo)",
        "serial": "99178834",
        "date": "2025-05-10",
        "url": "https://tsdr.uspto.gov/#caseNumber=99178834&caseSearchType=US_APPLICATION&caseType=DEFAULT&searchType=statusSearch"
      },
      {
        "category": "tech",
        "emoji": "\ud83d\udcbb",
        "applicant": "Reclusive Inc.",
        "mark": "CLOSED-CIRCUIT AI",
        "serial": "99179115",
        "date": "2025-05-10",
        "url": "https://tsdr.uspto.gov/#caseNumber=99179115&caseSearchType=US_APPLICATION&caseType=DEFAULT&searchType=statusSearch"
      },
      {
        "category": "tech",
        "emoji": "\ud83d\udcbb",
        "applicant": "Anbio (Xiamen) Biotechnology Co., Ltd.",
        "mark": "ANVET (& Logo)",
        "serial": "99178786",
        "date": "2025-05-10",
        "url": "https://tsdr.uspto.gov/#caseNumber=99178786&caseSearchType=US_APPLICATION&caseType=DEFAULT&searchType=statusSearch"
      },
      {
        "category": "tech",
        "emoji": "\ud83d\udcbb",
        "applicant": "Bookworms United, Inc.",
        "mark": "KOOBOOM",
        "serial": "99178823",
        "date": "2025-05-10",
        "url": "https://tsdr.uspto.gov/#caseNumber=99178823&caseSearchType=US_APPLICATION&caseType=DEFAULT&searchType=statusSearch"
      }
    ],
    "sports": [],
    "music": [],
    "entertainment": [
      {
        "category": "entertainment",
        "emoji": "\ud83c\udfac",
        "applicant": "Sun & Sol Co. LLC",
        "mark": "SUN&SOL",
        "serial": "99361997",
        "date": "2025-08-27",
        "url": "https://tsdr.uspto.gov/#caseNumber=99361997&caseSearchType=US_APPLICATION&caseType=DEFAULT&searchType=statusSearch"
      },
      {
        "category": "entertainment",
        "emoji": "\ud83c\udfac",
        "applicant": "Sun & Sol Co. LLC",
        "mark": "(Logo Only)",
        "serial": "99362027",
        "date": "2025-08-27",
        "url": "https://tsdr.uspto.gov/#caseNumber=99362027&caseSearchType=US_APPLICATION&caseType=DEFAULT&searchType=statusSearch"
      },
      {
        "category": "entertainment",
        "emoji": "\ud83c\udfac",
        "applicant": "Daniel Robert TARR-PINTER",
        "mark": "42NET (& Logo)",
        "serial": "99179012",
        "date": "2025-05-10",
        "url": "https://tsdr.uspto.gov/#caseNumber=99179012&caseSearchType=US_APPLICATION&caseType=DEFAULT&searchType=statusSearch"
      },
      {
        "category": "entertainment",
        "emoji": "\ud83c\udfac",
        "applicant": "cloaq media",
        "mark": "THE DARK ROOM",
        "serial": "99178852",
        "date": "2025-05-10",
        "url": "https://tsdr.uspto.gov/#caseNumber=99178852&caseSearchType=US_APPLICATION&caseType=DEFAULT&searchType=statusSearch"
      },
      {
        "category": "entertainment",
        "emoji": "\ud83c\udfac",
        "applicant": "Wendy Jimenez",
        "mark": "ANGEL ARTISTS",
        "serial": "99178898",
        "date": "2025-05-10",
        "url": "https://tsdr.uspto.gov/#caseNumber=99178898&caseSearchType=US_APPLICATION&caseType=DEFAULT&searchType=statusSearch"
      }
    ],
    "food": [
      {
        "category": "food",
        "emoji": "\ud83c\udf54",
        "applicant": "jnarazurum llc",
        "mark": "JNARA",
        "serial": "99178217",
        "date": "2025-05-11",
        "url": "https://tsdr.uspto.gov/#caseNumber=99178217&caseSearchType=US_APPLICATION&caseType=DEFAULT&searchType=statusSearch"
      },
      {
        "category": "food",
        "emoji": "\ud83c\udf54",
        "applicant": "Mission 618 Inc.",
        "mark": "CHICK CHICK",
        "serial": "99178923",
        "date": "2025-05-10",
        "url": "https://tsdr.uspto.gov/#caseNumber=99178923&caseSearchType=US_APPLICATION&caseType=DEFAULT&searchType=statusSearch"
      }
    ],
    "beverage": [
      {
        "category": "beverage",
        "emoji": "\ud83e\udd64",
        "applicant": "Andr\u00e9 Benjamin",
        "mark": "BENJI BIXBY",
        "serial": "99178824",
        "date": "2025-05-10",
        "url": "https://tsdr.uspto.gov/#caseNumber=99178824&caseSearchType=US_APPLICATION&caseType=DEFAULT&searchType=statusSearch"
      }
    ],
    "fashion": [
      {
        "category": "fashion",
        "emoji": "\ud83d\udc5f",
        "applicant": "William J Malamut Jr.",
        "mark": "NEON THEORY",
        "serial": "99361647",
        "date": "2025-08-27",
        "url": "https://tsdr.uspto.gov/#caseNumber=99361647&caseSearchType=US_APPLICATION&caseType=DEFAULT&searchType=statusSearch"
      },
      {
        "category": "fashion",
        "emoji": "\ud83d\udc5f",
        "applicant": "Wu Zhenggui",
        "mark": "DPZMH",
        "serial": "99361688",
        "date": "2025-08-27",
        "url": "https://tsdr.uspto.gov/#caseNumber=99361688&caseSearchType=US_APPLICATION&caseType=DEFAULT&searchType=statusSearch"
      },
      {
        "category": "fashion",
        "emoji": "\ud83d\udc5f",
        "applicant": "Shenzhen Zhiyuetong Trading Co., Ltd.",
        "mark": "SYLPHIDARA",
        "serial": "99361940",
        "date": "2025-08-27",
        "url": "https://tsdr.uspto.gov/#caseNumber=99361940&caseSearchType=US_APPLICATION&caseType=DEFAULT&searchType=statusSearch"
      },
      {
        "category": "fashion",
        "emoji": "\ud83d\udc5f",
        "applicant": "ZSJ DUGTIZ LLC",
        "mark": "LUCKOBI",
        "serial": "99359999",
        "date": "2025-08-27",
        "url": "https://tsdr.uspto.gov/#caseNumber=99359999&caseSearchType=US_APPLICATION&caseType=DEFAULT&searchType=statusSearch"
      },
      {
        "category": "fashion",
        "emoji": "\ud83d\udc5f",
        "applicant": "Etoni T Tonga",
        "mark": "SLON8VE",
        "serial": "99178906",
        "date": "2025-05-10",
        "url": "https://tsdr.uspto.gov/#caseNumber=99178906&caseSearchType=US_APPLICATION&caseType=DEFAULT&searchType=statusSearch"
      }
    ]
  }
}