{
  "lastUpdated": "2026-02-28T09:20:21.490212",
  "categories": {
    "auto": [
      {
        "category": "auto",
        "emoji": "\ud83d\ude97",
        "applicant": "Xiujie Wang",
        "mark": "HAVEHIDE",
        "serial": "99672812",
        "date": "2026-02-26",
        "url": "https://tsdr.uspto.gov/#caseNumber=99672812&caseSearchType=US_APPLICATION&caseType=DEFAULT&searchType=statusSearch"
      },
      {
        "category": "auto",
        "emoji": "\ud83d\ude97",
        "applicant": "Jesus E Perez",
        "mark": "JP DIESEL",
        "serial": "99672825",
        "date": "2026-02-26",
        "url": "https://tsdr.uspto.gov/#caseNumber=99672825&caseSearchType=US_APPLICATION&caseType=DEFAULT&searchType=statusSearch"
      },
      {
        "category": "auto",
        "emoji": "\ud83d\ude97",
        "applicant": "Rui'an Ruiyi Auto Parts Trading Co., Ltd",
        "mark": "RUYIX DRIVEGEAR",
        "serial": "99667586",
        "date": "2026-02-26",
        "url": "https://tsdr.uspto.gov/#caseNumber=99667586&caseSearchType=US_APPLICATION&caseType=DEFAULT&searchType=statusSearch"
      }
    ],
    "gaming": [
      {
        "category": "gaming",
        "emoji": "\ud83c\udfae",
        "applicant": "MC PROFESSIONAL SERVICES LLC",
        "mark": "AXERY",
        "serial": "99672842",
        "date": "2026-02-26",
        "url": "https://tsdr.uspto.gov/#caseNumber=99672842&caseSearchType=US_APPLICATION&caseType=DEFAULT&searchType=statusSearch"
      },
      {
        "category": "gaming",
        "emoji": "\ud83c\udfae",
        "applicant": "LIGHT & WONDER, INC.",
        "mark": "FAT N' HAPPY",
        "serial": "99178874",
        "date": "2025-05-10",
        "url": "https://tsdr.uspto.gov/#caseNumber=99178874&caseSearchType=US_APPLICATION&caseType=DEFAULT&searchType=statusSearch"
      }
    ],
    "crypto": [],
    "celebrities": [],
    "tech": [
      {
        "category": "tech",
        "emoji": "\ud83d\udcbb",
        "applicant": "HealthTales LLC",
        "mark": "GLP101",
        "serial": "99672848",
        "date": "2026-02-26",
        "url": "https://tsdr.uspto.gov/#caseNumber=99672848&caseSearchType=US_APPLICATION&caseType=DEFAULT&searchType=statusSearch"
      },
      {
        "category": "tech",
        "emoji": "\ud83d\udcbb",
        "applicant": "Arkane Studios",
        "mark": "ARKANE STUDIOS",
        "serial": "99672915",
        "date": "2026-02-26",
        "url": "https://tsdr.uspto.gov/#caseNumber=99672915&caseSearchType=US_APPLICATION&caseType=DEFAULT&searchType=statusSearch"
      },
      {
        "category": "tech",
        "emoji": "\ud83d\udcbb",
        "applicant": "CodeVet Labs, Inc.",
        "mark": "CODEVET",
        "serial": "99673004",
        "date": "2026-02-26",
        "url": "https://tsdr.uspto.gov/#caseNumber=99673004&caseSearchType=US_APPLICATION&caseType=DEFAULT&searchType=statusSearch"
      },
      {
        "category": "tech",
        "emoji": "\ud83d\udcbb",
        "applicant": "Shenzhen Baixinhui Technology Co., Ltd.",
        "mark": "ASIGNOVEL",
        "serial": "99673012",
        "date": "2026-02-26",
        "url": "https://tsdr.uspto.gov/#caseNumber=99673012&caseSearchType=US_APPLICATION&caseType=DEFAULT&searchType=statusSearch"
      },
      {
        "category": "tech",
        "emoji": "\ud83d\udcbb",
        "applicant": "Sales Tank LLC",
        "mark": "SALES TANK",
        "serial": "99673014",
        "date": "2026-02-26",
        "url": "https://tsdr.uspto.gov/#caseNumber=99673014&caseSearchType=US_APPLICATION&caseType=DEFAULT&searchType=statusSearch"
      },
      {
        "category": "tech",
        "emoji": "\ud83d\udcbb",
        "applicant": "Link Capital Solutions, LLC",
        "mark": "MOSTA",
        "serial": "99673052",
        "date": "2026-02-26",
        "url": "https://tsdr.uspto.gov/#caseNumber=99673052&caseSearchType=US_APPLICATION&caseType=DEFAULT&searchType=statusSearch"
      },
      {
        "category": "tech",
        "emoji": "\ud83d\udcbb",
        "applicant": "Lumay INC",
        "mark": "MYLU",
        "serial": "99673059",
        "date": "2026-02-26",
        "url": "https://tsdr.uspto.gov/#caseNumber=99673059&caseSearchType=US_APPLICATION&caseType=DEFAULT&searchType=statusSearch"
      },
      {
        "category": "tech",
        "emoji": "\ud83d\udcbb",
        "applicant": "Guangyuan Liang",
        "mark": "PBLKMH",
        "serial": "99673143",
        "date": "2026-02-26",
        "url": "https://tsdr.uspto.gov/#caseNumber=99673143&caseSearchType=US_APPLICATION&caseType=DEFAULT&searchType=statusSearch"
      },
      {
        "category": "tech",
        "emoji": "\ud83d\udcbb",
        "applicant": "Mymother Inc.",
        "mark": "MYMOTHER.AI",
        "serial": "99656883",
        "date": "2026-02-26",
        "url": "https://tsdr.uspto.gov/#caseNumber=99656883&caseSearchType=US_APPLICATION&caseType=DEFAULT&searchType=statusSearch"
      },
      {
        "category": "tech",
        "emoji": "\ud83d\udcbb",
        "applicant": "Linya Liu",
        "mark": "TEACHFAST",
        "serial": "99659563",
        "date": "2026-02-26",
        "url": "https://tsdr.uspto.gov/#caseNumber=99659563&caseSearchType=US_APPLICATION&caseType=DEFAULT&searchType=statusSearch"
      },
      {
        "category": "tech",
        "emoji": "\ud83d\udcbb",
        "applicant": "Caleb Edward Wilborn",
        "mark": "CLAWDADDY (& Logo)",
        "serial": "99668960",
        "date": "2026-02-26",
        "url": "https://tsdr.uspto.gov/#caseNumber=99668960&caseSearchType=US_APPLICATION&caseType=DEFAULT&searchType=statusSearch"
      },
      {
        "category": "tech",
        "emoji": "\ud83d\udcbb",
        "applicant": "Asaf Fulks",
        "mark": "STEMDESK",
        "serial": "99670978",
        "date": "2026-02-26",
        "url": "https://tsdr.uspto.gov/#caseNumber=99670978&caseSearchType=US_APPLICATION&caseType=DEFAULT&searchType=statusSearch"
      },
      {
        "category": "tech",
        "emoji": "\ud83d\udcbb",
        "applicant": "WERSUS Partners llc",
        "mark": "CLEARPROFIT",
        "serial": "99670979",
        "date": "2026-02-26",
        "url": "https://tsdr.uspto.gov/#caseNumber=99670979&caseSearchType=US_APPLICATION&caseType=DEFAULT&searchType=statusSearch"
      },
      {
        "category": "tech",
        "emoji": "\ud83d\udcbb",
        "applicant": "iPolish, Inc.",
        "mark": "I (& Logo)",
        "serial": "99179072",
        "date": "2025-05-10",
        "url": "https://tsdr.uspto.gov/#caseNumber=99179072&caseSearchType=US_APPLICATION&caseType=DEFAULT&searchType=statusSearch"
      },
      {
        "category": "tech",
        "emoji": "\ud83d\udcbb",
        "applicant": "Jenny Patrizia Lee",
        "mark": "EMOTIONAL SUPPORT AI",
        "serial": "99178810",
        "date": "2025-05-10",
        "url": "https://tsdr.uspto.gov/#caseNumber=99178810&caseSearchType=US_APPLICATION&caseType=DEFAULT&searchType=statusSearch"
      },
      {
        "category": "tech",
        "emoji": "\ud83d\udcbb",
        "applicant": "Aifection LLC",
        "mark": "HEARTCHIP",
        "serial": "99178827",
        "date": "2025-05-10",
        "url": "https://tsdr.uspto.gov/#caseNumber=99178827&caseSearchType=US_APPLICATION&caseType=DEFAULT&searchType=statusSearch"
      },
      {
        "category": "tech",
        "emoji": "\ud83d\udcbb",
        "applicant": "DiscoverFire.ai LLC",
        "mark": "DISCOVERFIRE AI (& Logo)",
        "serial": "99178834",
        "date": "2025-05-10",
        "url": "https://tsdr.uspto.gov/#caseNumber=99178834&caseSearchType=US_APPLICATION&caseType=DEFAULT&searchType=statusSearch"
      },
      {
        "category": "tech",
        "emoji": "\ud83d\udcbb",
        "applicant": "Reclusive Inc.",
        "mark": "CLOSED-CIRCUIT AI",
        "serial": "99179115",
        "date": "2025-05-10",
        "url": "https://tsdr.uspto.gov/#caseNumber=99179115&caseSearchType=US_APPLICATION&caseType=DEFAULT&searchType=statusSearch"
      },
      {
        "category": "tech",
        "emoji": "\ud83d\udcbb",
        "applicant": "Anbio (Xiamen) Biotechnology Co., Ltd.",
        "mark": "ANVET (& Logo)",
        "serial": "99178786",
        "date": "2025-05-10",
        "url": "https://tsdr.uspto.gov/#caseNumber=99178786&caseSearchType=US_APPLICATION&caseType=DEFAULT&searchType=statusSearch"
      },
      {
        "category": "tech",
        "emoji": "\ud83d\udcbb",
        "applicant": "Bookworms United, Inc.",
        "mark": "KOOBOOM",
        "serial": "99178823",
        "date": "2025-05-10",
        "url": "https://tsdr.uspto.gov/#caseNumber=99178823&caseSearchType=US_APPLICATION&caseType=DEFAULT&searchType=statusSearch"
      }
    ],
    "sports": [],
    "music": [],
    "entertainment": [
      {
        "category": "entertainment",
        "emoji": "\ud83c\udfac",
        "applicant": "Lamar D Decuir",
        "mark": "MAULY",
        "serial": "99642727",
        "date": "2026-02-26",
        "url": "https://tsdr.uspto.gov/#caseNumber=99642727&caseSearchType=US_APPLICATION&caseType=DEFAULT&searchType=statusSearch"
      },
      {
        "category": "entertainment",
        "emoji": "\ud83c\udfac",
        "applicant": "Daniel Robert TARR-PINTER",
        "mark": "42NET (& Logo)",
        "serial": "99179012",
        "date": "2025-05-10",
        "url": "https://tsdr.uspto.gov/#caseNumber=99179012&caseSearchType=US_APPLICATION&caseType=DEFAULT&searchType=statusSearch"
      },
      {
        "category": "entertainment",
        "emoji": "\ud83c\udfac",
        "applicant": "cloaq media",
        "mark": "THE DARK ROOM",
        "serial": "99178852",
        "date": "2025-05-10",
        "url": "https://tsdr.uspto.gov/#caseNumber=99178852&caseSearchType=US_APPLICATION&caseType=DEFAULT&searchType=statusSearch"
      },
      {
        "category": "entertainment",
        "emoji": "\ud83c\udfac",
        "applicant": "Wendy Jimenez",
        "mark": "ANGEL ARTISTS",
        "serial": "99178898",
        "date": "2025-05-10",
        "url": "https://tsdr.uspto.gov/#caseNumber=99178898&caseSearchType=US_APPLICATION&caseType=DEFAULT&searchType=statusSearch"
      }
    ],
    "food": [
      {
        "category": "food",
        "emoji": "\ud83c\udf54",
        "applicant": "The Mozz Pit",
        "mark": "THE MOZZ PIT",
        "serial": "99673109",
        "date": "2026-02-26",
        "url": "https://tsdr.uspto.gov/#caseNumber=99673109&caseSearchType=US_APPLICATION&caseType=DEFAULT&searchType=statusSearch"
      },
      {
        "category": "food",
        "emoji": "\ud83c\udf54",
        "applicant": "jnarazurum llc",
        "mark": "JNARA",
        "serial": "99178217",
        "date": "2025-05-11",
        "url": "https://tsdr.uspto.gov/#caseNumber=99178217&caseSearchType=US_APPLICATION&caseType=DEFAULT&searchType=statusSearch"
      },
      {
        "category": "food",
        "emoji": "\ud83c\udf54",
        "applicant": "Mission 618 Inc.",
        "mark": "CHICK CHICK",
        "serial": "99178923",
        "date": "2025-05-10",
        "url": "https://tsdr.uspto.gov/#caseNumber=99178923&caseSearchType=US_APPLICATION&caseType=DEFAULT&searchType=statusSearch"
      }
    ],
    "beverage": [
      {
        "category": "beverage",
        "emoji": "\ud83e\udd64",
        "applicant": "Zhanglu Feng",
        "mark": "BZHYYV",
        "serial": "99672827",
        "date": "2026-02-26",
        "url": "https://tsdr.uspto.gov/#caseNumber=99672827&caseSearchType=US_APPLICATION&caseType=DEFAULT&searchType=statusSearch"
      },
      {
        "category": "beverage",
        "emoji": "\ud83e\udd64",
        "applicant": "Zhuang Witian",
        "mark": "MDCGY",
        "serial": "99670982",
        "date": "2026-02-26",
        "url": "https://tsdr.uspto.gov/#caseNumber=99670982&caseSearchType=US_APPLICATION&caseType=DEFAULT&searchType=statusSearch"
      },
      {
        "category": "beverage",
        "emoji": "\ud83e\udd64",
        "applicant": "Andr\u00e9 Benjamin",
        "mark": "BENJI BIXBY",
        "serial": "99178824",
        "date": "2025-05-10",
        "url": "https://tsdr.uspto.gov/#caseNumber=99178824&caseSearchType=US_APPLICATION&caseType=DEFAULT&searchType=statusSearch"
      }
    ],
    "fashion": [
      {
        "category": "fashion",
        "emoji": "\ud83d\udc5f",
        "applicant": "Kevin E Perry",
        "mark": "MAISON \u00c9LU",
        "serial": "99669430",
        "date": "2026-02-26",
        "url": "https://tsdr.uspto.gov/#caseNumber=99669430&caseSearchType=US_APPLICATION&caseType=DEFAULT&searchType=statusSearch"
      },
      {
        "category": "fashion",
        "emoji": "\ud83d\udc5f",
        "applicant": "Etoni T Tonga",
        "mark": "SLON8VE",
        "serial": "99178906",
        "date": "2025-05-10",
        "url": "https://tsdr.uspto.gov/#caseNumber=99178906&caseSearchType=US_APPLICATION&caseType=DEFAULT&searchType=statusSearch"
      }
    ]
  }
}