{
  "lastUpdated": "2025-08-31T09:12:10.261175",
  "categories": {
    "auto": [
      {
        "category": "auto",
        "emoji": "\ud83d\ude97",
        "applicant": "Ruiling (Shanghai) Automotive Technology Co., Ltd.",
        "mark": "KS",
        "serial": "99366618",
        "date": "2025-08-29",
        "url": "https://tsdr.uspto.gov/#caseNumber=99366618&caseSearchType=US_APPLICATION&caseType=DEFAULT&searchType=statusSearch"
      }
    ],
    "gaming": [
      {
        "category": "gaming",
        "emoji": "\ud83c\udfae",
        "applicant": "LIGHT & WONDER, INC.",
        "mark": "FAT N' HAPPY",
        "serial": "99178874",
        "date": "2025-05-10",
        "url": "https://tsdr.uspto.gov/#caseNumber=99178874&caseSearchType=US_APPLICATION&caseType=DEFAULT&searchType=statusSearch"
      }
    ],
    "crypto": [],
    "celebrities": [],
    "tech": [
      {
        "category": "tech",
        "emoji": "\ud83d\udcbb",
        "applicant": "TRAICE Labs Corporation",
        "mark": "TRAICE",
        "serial": "99366408",
        "date": "2025-08-29",
        "url": "https://tsdr.uspto.gov/#caseNumber=99366408&caseSearchType=US_APPLICATION&caseType=DEFAULT&searchType=statusSearch"
      },
      {
        "category": "tech",
        "emoji": "\ud83d\udcbb",
        "applicant": "Shenzhen Lishuo New Energy Technology Co., Ltd.",
        "mark": "GANJIUXINGL",
        "serial": "99366414",
        "date": "2025-08-29",
        "url": "https://tsdr.uspto.gov/#caseNumber=99366414&caseSearchType=US_APPLICATION&caseType=DEFAULT&searchType=statusSearch"
      },
      {
        "category": "tech",
        "emoji": "\ud83d\udcbb",
        "applicant": "Saige, Inc.",
        "mark": "SAIGE",
        "serial": "99366440",
        "date": "2025-08-29",
        "url": "https://tsdr.uspto.gov/#caseNumber=99366440&caseSearchType=US_APPLICATION&caseType=DEFAULT&searchType=statusSearch"
      },
      {
        "category": "tech",
        "emoji": "\ud83d\udcbb",
        "applicant": "Satlyt Inc",
        "mark": "THE ABOVE CLOUD SERVICE PROVIDER",
        "serial": "99366454",
        "date": "2025-08-29",
        "url": "https://tsdr.uspto.gov/#caseNumber=99366454&caseSearchType=US_APPLICATION&caseType=DEFAULT&searchType=statusSearch"
      },
      {
        "category": "tech",
        "emoji": "\ud83d\udcbb",
        "applicant": "DRAGONPLUS GAME LIMITED",
        "mark": "D\u00c9CORER: MERGE HOME MASTER",
        "serial": "99366460",
        "date": "2025-08-29",
        "url": "https://tsdr.uspto.gov/#caseNumber=99366460&caseSearchType=US_APPLICATION&caseType=DEFAULT&searchType=statusSearch"
      },
      {
        "category": "tech",
        "emoji": "\ud83d\udcbb",
        "applicant": "TRAICE Labs Corporation",
        "mark": "HUGE HUMAN MODEL",
        "serial": "99366463",
        "date": "2025-08-29",
        "url": "https://tsdr.uspto.gov/#caseNumber=99366463&caseSearchType=US_APPLICATION&caseType=DEFAULT&searchType=statusSearch"
      },
      {
        "category": "tech",
        "emoji": "\ud83d\udcbb",
        "applicant": "Sandisk Technologies, Inc.",
        "mark": "QUICKFLOW (& Logo)",
        "serial": "99366467",
        "date": "2025-08-29",
        "url": "https://tsdr.uspto.gov/#caseNumber=99366467&caseSearchType=US_APPLICATION&caseType=DEFAULT&searchType=statusSearch"
      },
      {
        "category": "tech",
        "emoji": "\ud83d\udcbb",
        "applicant": "The SDET Playbook, LLC",
        "mark": "THE SDET PLAYBOOK",
        "serial": "99366487",
        "date": "2025-08-29",
        "url": "https://tsdr.uspto.gov/#caseNumber=99366487&caseSearchType=US_APPLICATION&caseType=DEFAULT&searchType=statusSearch"
      },
      {
        "category": "tech",
        "emoji": "\ud83d\udcbb",
        "applicant": "Jung Sun SO",
        "mark": "EMOPILOT",
        "serial": "99366489",
        "date": "2025-08-29",
        "url": "https://tsdr.uspto.gov/#caseNumber=99366489&caseSearchType=US_APPLICATION&caseType=DEFAULT&searchType=statusSearch"
      },
      {
        "category": "tech",
        "emoji": "\ud83d\udcbb",
        "applicant": "Long Phuoc Nguyen",
        "mark": "VIVA VPN",
        "serial": "99366491",
        "date": "2025-08-29",
        "url": "https://tsdr.uspto.gov/#caseNumber=99366491&caseSearchType=US_APPLICATION&caseType=DEFAULT&searchType=statusSearch"
      },
      {
        "category": "tech",
        "emoji": "\ud83d\udcbb",
        "applicant": "Saige, Inc.",
        "mark": "SAIGE",
        "serial": "99366497",
        "date": "2025-08-29",
        "url": "https://tsdr.uspto.gov/#caseNumber=99366497&caseSearchType=US_APPLICATION&caseType=DEFAULT&searchType=statusSearch"
      },
      {
        "category": "tech",
        "emoji": "\ud83d\udcbb",
        "applicant": "QuSecure, Inc",
        "mark": "QUPROTECT RESILIENCE (& Logo)",
        "serial": "99366507",
        "date": "2025-08-29",
        "url": "https://tsdr.uspto.gov/#caseNumber=99366507&caseSearchType=US_APPLICATION&caseType=DEFAULT&searchType=statusSearch"
      },
      {
        "category": "tech",
        "emoji": "\ud83d\udcbb",
        "applicant": "Lume Women + Health Inc.",
        "mark": "LUME LONGEVITY INSTITUTE",
        "serial": "99366531",
        "date": "2025-08-29",
        "url": "https://tsdr.uspto.gov/#caseNumber=99366531&caseSearchType=US_APPLICATION&caseType=DEFAULT&searchType=statusSearch"
      },
      {
        "category": "tech",
        "emoji": "\ud83d\udcbb",
        "applicant": "Anteros App LLC",
        "mark": "ANTEROS",
        "serial": "99366552",
        "date": "2025-08-29",
        "url": "https://tsdr.uspto.gov/#caseNumber=99366552&caseSearchType=US_APPLICATION&caseType=DEFAULT&searchType=statusSearch"
      },
      {
        "category": "tech",
        "emoji": "\ud83d\udcbb",
        "applicant": "Wen Tang",
        "mark": "DCXIO (& Logo)",
        "serial": "99366558",
        "date": "2025-08-29",
        "url": "https://tsdr.uspto.gov/#caseNumber=99366558&caseSearchType=US_APPLICATION&caseType=DEFAULT&searchType=statusSearch"
      },
      {
        "category": "tech",
        "emoji": "\ud83d\udcbb",
        "applicant": "Vegas Meg LLC",
        "mark": "VEGAS MEG (& Logo)",
        "serial": "99366591",
        "date": "2025-08-29",
        "url": "https://tsdr.uspto.gov/#caseNumber=99366591&caseSearchType=US_APPLICATION&caseType=DEFAULT&searchType=statusSearch"
      },
      {
        "category": "tech",
        "emoji": "\ud83d\udcbb",
        "applicant": "Mythic Inc.",
        "mark": "M (& Logo)",
        "serial": "99366596",
        "date": "2025-08-29",
        "url": "https://tsdr.uspto.gov/#caseNumber=99366596&caseSearchType=US_APPLICATION&caseType=DEFAULT&searchType=statusSearch"
      },
      {
        "category": "tech",
        "emoji": "\ud83d\udcbb",
        "applicant": "Charles Douglas Barr Jr",
        "mark": "V\u0100K NA\u016aRA (& Logo)",
        "serial": "99364946",
        "date": "2025-08-29",
        "url": "https://tsdr.uspto.gov/#caseNumber=99364946&caseSearchType=US_APPLICATION&caseType=DEFAULT&searchType=statusSearch"
      },
      {
        "category": "tech",
        "emoji": "\ud83d\udcbb",
        "applicant": "Azstar IT Corporation",
        "mark": "GROVESTAY",
        "serial": "99364950",
        "date": "2025-08-29",
        "url": "https://tsdr.uspto.gov/#caseNumber=99364950&caseSearchType=US_APPLICATION&caseType=DEFAULT&searchType=statusSearch"
      },
      {
        "category": "tech",
        "emoji": "\ud83d\udcbb",
        "applicant": "iPolish, Inc.",
        "mark": "I (& Logo)",
        "serial": "99179072",
        "date": "2025-05-10",
        "url": "https://tsdr.uspto.gov/#caseNumber=99179072&caseSearchType=US_APPLICATION&caseType=DEFAULT&searchType=statusSearch"
      }
    ],
    "sports": [
      {
        "category": "sports",
        "emoji": "\u26bd",
        "applicant": "Zhuhai Huanfu Trading Co., Ltd.",
        "mark": "COREHARMONY",
        "serial": "99366410",
        "date": "2025-08-29",
        "url": "https://tsdr.uspto.gov/#caseNumber=99366410&caseSearchType=US_APPLICATION&caseType=DEFAULT&searchType=statusSearch"
      },
      {
        "category": "sports",
        "emoji": "\u26bd",
        "applicant": "2 PM IP Holdings, LLC",
        "mark": "MAHOMES BRAND",
        "serial": "99366545",
        "date": "2025-08-29",
        "url": "https://tsdr.uspto.gov/#caseNumber=99366545&caseSearchType=US_APPLICATION&caseType=DEFAULT&searchType=statusSearch"
      }
    ],
    "music": [
      {
        "category": "music",
        "emoji": "\ud83c\udfb5",
        "applicant": "Asia Anastasia Morgan",
        "mark": "ASIA ANASTASIA",
        "serial": "99366573",
        "date": "2025-08-29",
        "url": "https://tsdr.uspto.gov/#caseNumber=99366573&caseSearchType=US_APPLICATION&caseType=DEFAULT&searchType=statusSearch"
      },
      {
        "category": "music",
        "emoji": "\ud83c\udfb5",
        "applicant": "Nana He",
        "mark": "OWNSOGA",
        "serial": "99366594",
        "date": "2025-08-29",
        "url": "https://tsdr.uspto.gov/#caseNumber=99366594&caseSearchType=US_APPLICATION&caseType=DEFAULT&searchType=statusSearch"
      }
    ],
    "entertainment": [
      {
        "category": "entertainment",
        "emoji": "\ud83c\udfac",
        "applicant": "Rolling Sheep Productions, LLC",
        "mark": "(Logo Only)",
        "serial": "99366320",
        "date": "2025-08-29",
        "url": "https://tsdr.uspto.gov/#caseNumber=99366320&caseSearchType=US_APPLICATION&caseType=DEFAULT&searchType=statusSearch"
      },
      {
        "category": "entertainment",
        "emoji": "\ud83c\udfac",
        "applicant": "Rolling Sheep Productions, LLC",
        "mark": "(Logo Only)",
        "serial": "99366328",
        "date": "2025-08-29",
        "url": "https://tsdr.uspto.gov/#caseNumber=99366328&caseSearchType=US_APPLICATION&caseType=DEFAULT&searchType=statusSearch"
      },
      {
        "category": "entertainment",
        "emoji": "\ud83c\udfac",
        "applicant": "Robert C. Hoffman",
        "mark": "CHA$ING ARTHUR",
        "serial": "99366566",
        "date": "2025-08-29",
        "url": "https://tsdr.uspto.gov/#caseNumber=99366566&caseSearchType=US_APPLICATION&caseType=DEFAULT&searchType=statusSearch"
      },
      {
        "category": "entertainment",
        "emoji": "\ud83c\udfac",
        "applicant": "Daniel Robert TARR-PINTER",
        "mark": "42NET (& Logo)",
        "serial": "99179012",
        "date": "2025-05-10",
        "url": "https://tsdr.uspto.gov/#caseNumber=99179012&caseSearchType=US_APPLICATION&caseType=DEFAULT&searchType=statusSearch"
      },
      {
        "category": "entertainment",
        "emoji": "\ud83c\udfac",
        "applicant": "cloaq media",
        "mark": "THE DARK ROOM",
        "serial": "99178852",
        "date": "2025-05-10",
        "url": "https://tsdr.uspto.gov/#caseNumber=99178852&caseSearchType=US_APPLICATION&caseType=DEFAULT&searchType=statusSearch"
      },
      {
        "category": "entertainment",
        "emoji": "\ud83c\udfac",
        "applicant": "Wendy Jimenez",
        "mark": "ANGEL ARTISTS",
        "serial": "99178898",
        "date": "2025-05-10",
        "url": "https://tsdr.uspto.gov/#caseNumber=99178898&caseSearchType=US_APPLICATION&caseType=DEFAULT&searchType=statusSearch"
      }
    ],
    "food": [
      {
        "category": "food",
        "emoji": "\ud83c\udf54",
        "applicant": "Jude Living LLC",
        "mark": "JUDE",
        "serial": "99366381",
        "date": "2025-08-29",
        "url": "https://tsdr.uspto.gov/#caseNumber=99366381&caseSearchType=US_APPLICATION&caseType=DEFAULT&searchType=statusSearch"
      },
      {
        "category": "food",
        "emoji": "\ud83c\udf54",
        "applicant": "Yimin Zhou",
        "mark": "RAPTAIR",
        "serial": "99366401",
        "date": "2025-08-29",
        "url": "https://tsdr.uspto.gov/#caseNumber=99366401&caseSearchType=US_APPLICATION&caseType=DEFAULT&searchType=statusSearch"
      },
      {
        "category": "food",
        "emoji": "\ud83c\udf54",
        "applicant": "Every Little Thing Holdings LLC",
        "mark": "MAJOR YUM",
        "serial": "99364915",
        "date": "2025-08-29",
        "url": "https://tsdr.uspto.gov/#caseNumber=99364915&caseSearchType=US_APPLICATION&caseType=DEFAULT&searchType=statusSearch"
      },
      {
        "category": "food",
        "emoji": "\ud83c\udf54",
        "applicant": "jnarazurum llc",
        "mark": "JNARA",
        "serial": "99178217",
        "date": "2025-05-11",
        "url": "https://tsdr.uspto.gov/#caseNumber=99178217&caseSearchType=US_APPLICATION&caseType=DEFAULT&searchType=statusSearch"
      },
      {
        "category": "food",
        "emoji": "\ud83c\udf54",
        "applicant": "Mission 618 Inc.",
        "mark": "CHICK CHICK",
        "serial": "99178923",
        "date": "2025-05-10",
        "url": "https://tsdr.uspto.gov/#caseNumber=99178923&caseSearchType=US_APPLICATION&caseType=DEFAULT&searchType=statusSearch"
      }
    ],
    "beverage": [
      {
        "category": "beverage",
        "emoji": "\ud83e\udd64",
        "applicant": "Andr\u00e9 Benjamin",
        "mark": "BENJI BIXBY",
        "serial": "99178824",
        "date": "2025-05-10",
        "url": "https://tsdr.uspto.gov/#caseNumber=99178824&caseSearchType=US_APPLICATION&caseType=DEFAULT&searchType=statusSearch"
      }
    ],
    "fashion": [
      {
        "category": "fashion",
        "emoji": "\ud83d\udc5f",
        "applicant": "WU-WEI FASHION LAB LLC",
        "mark": "WU WEI FASHION LAB",
        "serial": "99366504",
        "date": "2025-08-29",
        "url": "https://tsdr.uspto.gov/#caseNumber=99366504&caseSearchType=US_APPLICATION&caseType=DEFAULT&searchType=statusSearch"
      },
      {
        "category": "fashion",
        "emoji": "\ud83d\udc5f",
        "applicant": "Steve Austin Kotright",
        "mark": "EDEN SLOPE",
        "serial": "99366556",
        "date": "2025-08-29",
        "url": "https://tsdr.uspto.gov/#caseNumber=99366556&caseSearchType=US_APPLICATION&caseType=DEFAULT&searchType=statusSearch"
      },
      {
        "category": "fashion",
        "emoji": "\ud83d\udc5f",
        "applicant": "Elijah d Reynolds",
        "mark": "KOUNT",
        "serial": "99366579",
        "date": "2025-08-29",
        "url": "https://tsdr.uspto.gov/#caseNumber=99366579&caseSearchType=US_APPLICATION&caseType=DEFAULT&searchType=statusSearch"
      },
      {
        "category": "fashion",
        "emoji": "\ud83d\udc5f",
        "applicant": "North Carolina Wesleyan University, Incorporated",
        "mark": "W",
        "serial": "99364930",
        "date": "2025-08-29",
        "url": "https://tsdr.uspto.gov/#caseNumber=99364930&caseSearchType=US_APPLICATION&caseType=DEFAULT&searchType=statusSearch"
      },
      {
        "category": "fashion",
        "emoji": "\ud83d\udc5f",
        "applicant": "Etoni T Tonga",
        "mark": "SLON8VE",
        "serial": "99178906",
        "date": "2025-05-10",
        "url": "https://tsdr.uspto.gov/#caseNumber=99178906&caseSearchType=US_APPLICATION&caseType=DEFAULT&searchType=statusSearch"
      }
    ]
  }
}